<?xml version="1.0" encoding="utf-8"?>
<Model>
  <!--DEFAULT COMMAND-->
  <Command Name="__default_command" IsBranch="false" IsDefault="true" 
ClrType="EasyDotnet.IDE.Commands.RunCommand" 
Settings="EasyDotnet.IDE.Commands.RunCommand+Settings">
    <Parameters>
      <Option Short="" Long="logLevel" Value="LEVEL" Required="false" 
Kind="scalar" ClrType="System.Diagnostics.SourceLevels">
        <Description>Logging verbosity (Off, Critical, Error, Warning, 
Information, Verbose, All). Default: Off</Description>
      </Option>
    </Parameters>
  </Command>
  <!--GENERATE-RPC-DOCS-->
  <Command Name="generate-rpc-docs" IsBranch="false" 
ClrType="EasyDotnet.IDE.Commands.GenerateRpcDocsCommand" 
Settings="EasyDotnet.IDE.Commands.GenerateRpcDocsCommand+Settings">
    <Description>Generate RPC documentation in JSON or Markdown 
format.</Description>
    <Parameters>
      <Option Short="" Long="format" Value="FORMAT" Required="false" 
Kind="scalar" ClrType="System.String">
        <Description>Output format: 'json' (default) or 
'markdown'.</Description>
      </Option>
    </Parameters>
  </Command>
  <!--COMPAT-->
  <Command Name="compat" IsBranch="true" 
Settings="Spectre.Console.Cli.CommandSettings">
    <Description>Run compatibility commands (run, build, test).</Description>
    <!--RUN-->
    <Command Name="run" IsBranch="false" 
ClrType="EasyDotnet.IDE.Commands.CompatRunCommand" 
Settings="EasyDotnet.IDE.Commands.CompatRunCommand+Settings">
      <Description>Build and run a project, optionally under IIS 
Express.</Description>
      <Parameters>
        <Argument Name="PROJECT" Position="0" Required="true" Kind="scalar" 
ClrType="System.String">
          <Description>Path to the project file (.csproj).</Description>
        </Argument>
        <Option Short="" Long="msbuild" Value="PATH" Required="false" 
Kind="scalar" ClrType="System.String">
          <Description>Path to MSBuild.exe.</Description>
        </Option>
        <Option Short="" Long="target" Value="PATH" Required="false" 
Kind="scalar" ClrType="System.String">
          <Description>Path to compiled target executable.</Description>
        </Option>
      </Parameters>
    </Command>
    <!--BUILD-->
    <Command Name="build" IsBranch="false" 
ClrType="EasyDotnet.IDE.Commands.CompatBuildCommand" 
Settings="EasyDotnet.IDE.Commands.CompatBuildCommand+Settings">
      <Description>Build a project using MSBuild.</Description>
      <Parameters>
        <Argument Name="PROJECT" Position="0" Required="true" Kind="scalar" 
ClrType="System.String">
          <Description>Path to the project file (.csproj).</Description>
        </Argument>
        <Option Short="" Long="msbuild" Value="PATH" Required="false" 
Kind="scalar" ClrType="System.String">
          <Description>Path to MSBuild.exe.</Description>
        </Option>
      </Parameters>
    </Command>
    <!--TEST-->
    <Command Name="test" IsBranch="false" 
ClrType="EasyDotnet.IDE.Commands.CompatTestCommand" 
Settings="EasyDotnet.IDE.Commands.CompatTestCommand+Settings">
      <Description>Build and run tests using VSTest.</Description>
      <Parameters>
        <Argument Name="PROJECT" Position="0" Required="true" Kind="scalar" 
ClrType="System.String">
          <Description>Path to the project file (.csproj).</Description>
        </Argument>
        <Option Short="" Long="msbuild" Value="PATH" Required="false" 
Kind="scalar" ClrType="System.String">
          <Description>Path to MSBuild.exe.</Description>
        </Option>
        <Option Short="" Long="target" Value="PATH" Required="false" 
Kind="scalar" ClrType="System.String">
          <Description>Path to the test assembly (e.g., 
MyTests.dll).</Description>
        </Option>
        <Option Short="" Long="vstest" Value="PATH" Required="false" 
Kind="scalar" ClrType="System.String">
          <Description>Path to vstest.console.exe.</Description>
        </Option>
      </Parameters>
    </Command>
  </Command>
</Model>