{
  "opencli": "0.1-draft",
  "info": {
    "title": "FluentPulumiCli",
    "version": "0.1.1-CI.28"
  },
  "x-inspectra": {
    "artifactSource": "crawled-from-help",
    "generator": "InSpectra.Discovery",
    "helpDocumentCount": 5,
    "cliFramework": "System.CommandLine"
  },
  "commands": [
    {
      "name": "generate",
      "hidden": false,
      "description": "Command for generating pulumi import file for resource group",
      "options": [
        {
          "name": "--remove",
          "recursive": false,
          "hidden": false,
          "description": "Space seperated list with type name that should not be imported",
          "arguments": [
            {
              "name": "REMOVE",
              "required": true,
              "arity": {
                "minimum": 1,
                "maximum": 1
              }
            }
          ]
        },
        {
          "name": "--help",
          "recursive": false,
          "hidden": false,
          "description": "Show help and usage information",
          "aliases": [
            "-?",
            "-h"
          ]
        }
      ],
      "arguments": [
        {
          "name": "RESOURCEGROUPNAME",
          "required": true,
          "hidden": false,
          "arity": {
            "minimum": 1,
            "maximum": 1
          },
          "description": "The resource group name"
        },
        {
          "name": "INPUTSTACK",
          "required": true,
          "hidden": false,
          "arity": {
            "minimum": 1,
            "maximum": 1
          },
          "description": "The stack to add all resources to"
        }
      ]
    },
    {
      "name": "getwebappid",
      "hidden": false,
      "description": "Command for retrieving web app/function app ids. One id on each line",
      "options": [
        {
          "name": "--help",
          "recursive": false,
          "hidden": false,
          "description": "Show help and usage information",
          "aliases": [
            "-?",
            "-h"
          ]
        }
      ],
      "arguments": [
        {
          "name": "INPUTSTACK",
          "required": true,
          "hidden": false,
          "arity": {
            "minimum": 1,
            "maximum": 1
          },
          "description": "The current pulumi stack"
        }
      ]
    },
    {
      "name": "getwebappslotidsjson",
      "hidden": false,
      "description": "Command for retrieving web app slot/function app slot ids. One id on each line",
      "options": [
        {
          "name": "--help",
          "recursive": false,
          "hidden": false,
          "description": "Show help and usage information",
          "aliases": [
            "-?",
            "-h"
          ]
        }
      ],
      "arguments": [
        {
          "name": "INPUTSTACK",
          "required": true,
          "hidden": false,
          "arity": {
            "minimum": 1,
            "maximum": 1
          },
          "description": "The current pulumi stack"
        }
      ]
    },
    {
      "name": "importrole",
      "hidden": false,
      "description": "Command for importing roles from azure ad to role file",
      "options": [
        {
          "name": "--environment",
          "recursive": false,
          "hidden": false,
          "description": "Explicit define which environment should be used. This will return an error if more then one application is found",
          "arguments": [
            {
              "name": "ENVIRONMENT",
              "required": true,
              "arity": {
                "minimum": 1,
                "maximum": 1
              }
            }
          ]
        },
        {
          "name": "--help",
          "recursive": false,
          "hidden": false,
          "description": "Show help and usage information",
          "aliases": [
            "-?",
            "-h"
          ]
        }
      ],
      "arguments": [
        {
          "name": "ADAPPNAME",
          "required": true,
          "hidden": false,
          "arity": {
            "minimum": 1,
            "maximum": 1
          },
          "description": "The name or prefix name of the ad application"
        },
        {
          "name": "ROLEFILE",
          "required": true,
          "hidden": false,
          "arity": {
            "minimum": 1,
            "maximum": 1
          },
          "description": "The role file for pulumi"
        }
      ]
    }
  ],
  "options": [
    {
      "name": "--version",
      "recursive": false,
      "hidden": false,
      "description": "Show version information"
    },
    {
      "name": "--help",
      "recursive": false,
      "hidden": false,
      "description": "Show help and usage information",
      "aliases": [
        "-?",
        "-h"
      ]
    }
  ]
}
