{
  "schemaVersion": 1,
  "packageId": "sw",
  "version": "1.7.43-g0939e54b92",
  "trusted": false,
  "currentStatus": "success",
  "lastDisposition": "success",
  "attemptCount": 1,
  "consecutiveFailureCount": 0,
  "lastFailureSignature": null,
  "lastFailurePhase": null,
  "lastFailureMessage": null,
  "firstEvaluatedAt": "2026-03-30T01:08:07.7247348+00:00",
  "lastEvaluatedAt": "2026-03-30T01:08:07.7247348+00:00",
  "lastBatchId": "current-backfill-main-20260330t00434775972670000-001",
  "retryEligible": false,
  "nextAttemptAt": null,
  "lastSuccessfulAt": "2026-03-30T01:08:07.7247348+00:00",
  "indexedPaths": {
    "metadataPath": "index/packages/sw/1.7.43-g0939e54b92/metadata.json",
    "crawlPath": "index/packages/sw/1.7.43-g0939e54b92/crawl.json"
  }
}
