<?xml version="1.0" encoding="utf-8"?>
<Model>
  <!--DEFAULT COMMAND-->
  <Command Name="__default_command" IsBranch="false" IsDefault="true" 
ClrType="HttpGenerator.GenerateCommand" Settings="HttpGenerator.Settings">
    <Parameters>
      <Argument Name="URL or input file" Position="0" Required="false" 
Kind="scalar" ClrType="System.String">
        <Description>URL or file path to OpenAPI Specification 
file</Description>
      </Argument>
      <Option Short="" Long="no-logging" Value="NULL" Required="false" 
Kind="flag" ClrType="System.Boolean">
        <Description>Don't log errors or collect telemetry</Description>
      </Option>
      <Option Short="o" Long="output" Value="OUTPUT" Required="false" 
Kind="scalar" ClrType="System.String">
        <Description>Output directory</Description>
      </Option>
    </Parameters>
  </Command>
</Model>