{
  "documentCount": 1,
  "commandCount": 1,
  "captureCount": 1,
  "commands": [
    {
      "command": null,
      "helpInvocation": "--help",
      "result": {
        "status": "ok",
        "timedOut": false,
        "exitCode": 0,
        "durationMs": 204,
        "stdout": "USAGE:\n    OneS.MediateS.Cli.dll [OPTIONS]\n\nOPTIONS:\n    -h, --help    Prints help information\n    -i, --info",
        "stderr": null
      },
      "parsed": true,
      "payload": "USAGE:\n    OneS.MediateS.Cli.dll [OPTIONS]\n\nOPTIONS:\n    -h, --help    Prints help information\n    -i, --info",
      "terminalNonHelp": false
    }
  ]
}
