<?xml version="1.0" encoding="utf-8"?>
<Model>
  <!--COMMIT-->
  <Command Name="commit" IsBranch="false" ClrType="GitCommitCommand" 
Settings="GitCommitCommand+Settings">
    <Description>Commit staged changes using generated message</Description>
    <Examples>
      <Example commandLine="commit" />
      <Example commandLine="commit" />
      <Example commandLine="--debug" />
    </Examples>
  </Command>
  <!--CODE-->
  <Command Name="code" IsBranch="false" ClrType="CodeCommand" 
Settings="CodeCommand+Settings">
    <Description>Complete code in opened VSCode file</Description>
    <Examples>
      <Example commandLine="code" />
      <Example commandLine="code" />
      <Example commandLine="--debug" />
    </Examples>
  </Command>
</Model>