{
  "schemaVersion": 1,
  "packageId": "nugraph",
  "trusted": false,
  "totalDownloads": 1139,
  "links": {
    "nuget": "https://www.nuget.org/packages/nugraph",
    "project": "https://github.com/0xced/nugraph",
    "source": "https://github.com/0xced/nugraph"
  },
  "latestVersion": "0.5.0",
  "latestStatus": "partial",
  "latestPaths": {
    "metadataPath": "index/packages/nugraph/latest/metadata.json",
    "opencliPath": "index/packages/nugraph/latest/opencli.json",
    "xmldocPath": "index/packages/nugraph/latest/xmldoc.xml"
  },
  "versions": [
    {
      "version": "0.5.0",
      "publishedAt": "2025-06-27T20:45:47.7030000+00:00",
      "evaluatedAt": "2026-03-25T17:29:26.8031109+00:00",
      "status": "partial",
      "command": "nugraph",
      "timings": {
        "totalMs": 4605,
        "installMs": 2318,
        "opencliMs": 201,
        "xmldocMs": 156
      },
      "paths": {
        "metadataPath": "index/packages/nugraph/0.5.0/metadata.json",
        "opencliPath": "index/packages/nugraph/0.5.0/opencli.json",
        "xmldocPath": "index/packages/nugraph/0.5.0/xmldoc.xml",
        "opencliSource": "synthesized-from-xmldoc"
      }
    },
    {
      "version": "0.4.0",
      "publishedAt": "2025-06-26T14:48:01.3370000+00:00",
      "evaluatedAt": "2026-03-26T10:28:01.6850044+00:00",
      "status": "partial",
      "command": "nugraph",
      "timings": {
        "totalMs": 7759,
        "installMs": 5799,
        "opencliMs": 252,
        "xmldocMs": 148
      },
      "paths": {
        "metadataPath": "index/packages/nugraph/0.4.0/metadata.json",
        "opencliPath": "index/packages/nugraph/0.4.0/opencli.json",
        "opencliSource": "synthesized-from-xmldoc",
        "xmldocPath": "index/packages/nugraph/0.4.0/xmldoc.xml"
      }
    },
    {
      "version": "0.3.0",
      "publishedAt": "2025-06-24T14:48:34.9300000+00:00",
      "evaluatedAt": "2026-03-26T10:27:57.1701057+00:00",
      "status": "partial",
      "command": "nugraph",
      "timings": {
        "totalMs": 6027,
        "installMs": 4149,
        "opencliMs": 200,
        "xmldocMs": 149
      },
      "paths": {
        "metadataPath": "index/packages/nugraph/0.3.0/metadata.json",
        "opencliPath": "index/packages/nugraph/0.3.0/opencli.json",
        "opencliSource": "synthesized-from-xmldoc",
        "xmldocPath": "index/packages/nugraph/0.3.0/xmldoc.xml"
      }
    },
    {
      "version": "0.2.0",
      "publishedAt": "1900-01-01T00:00:00.0000000+00:00",
      "evaluatedAt": "2026-03-26T10:27:53.6047245+00:00",
      "status": "partial",
      "command": "nugraph",
      "timings": {
        "totalMs": 6066,
        "installMs": 3978,
        "opencliMs": 203,
        "xmldocMs": 151
      },
      "paths": {
        "metadataPath": "index/packages/nugraph/0.2.0/metadata.json",
        "opencliPath": "index/packages/nugraph/0.2.0/opencli.json",
        "opencliSource": "synthesized-from-xmldoc",
        "xmldocPath": "index/packages/nugraph/0.2.0/xmldoc.xml"
      }
    },
    {
      "version": "0.1.0-beta.1",
      "publishedAt": "1900-01-01T00:00:00.0000000+00:00",
      "evaluatedAt": "2026-03-26T10:27:42.3156744+00:00",
      "status": "partial",
      "command": "nugraph",
      "timings": {
        "totalMs": 4879,
        "installMs": 3086,
        "opencliMs": 201,
        "xmldocMs": 137
      },
      "paths": {
        "metadataPath": "index/packages/nugraph/0.1.0-beta.1/metadata.json",
        "opencliPath": "index/packages/nugraph/0.1.0-beta.1/opencli.json",
        "opencliSource": "synthesized-from-xmldoc",
        "xmldocPath": "index/packages/nugraph/0.1.0-beta.1/xmldoc.xml"
      }
    }
  ]
}
