{
  "schemaVersion": 1,
  "packageId": "SphereRabbitMQ.IaC.Tool",
  "trusted": false,
  "totalDownloads": 1538,
  "links": {
    "nuget": "https://www.nuget.org/packages/SphereRabbitMQ.IaC.Tool",
    "project": null,
    "source": "https://github.com/PinedaTec.eu/SphereRabbitMQ"
  },
  "latestVersion": "0.1.4.102",
  "latestStatus": "ok",
  "versions": [
    {
      "version": "0.1.4.102",
      "publishedAt": "2026-03-30T17:37:09.8970000+00:00",
      "evaluatedAt": "2026-03-31T13:46:19.3626309+00:00",
      "status": "ok",
      "command": "sprmq",
      "timings": {
        "totalMs": 2139,
        "installMs": 1494,
        "opencliMs": null,
        "xmldocMs": null,
        "crawlMs": 504
      },
      "paths": {
        "metadataPath": "index/packages/sphererabbitmq.iac.tool/0.1.4.102/metadata.json",
        "opencliPath": "index/packages/sphererabbitmq.iac.tool/0.1.4.102/opencli.json",
        "opencliSource": "startup-hook"
      },
      "cliFramework": "System.CommandLine"
    }
  ],
  "cliFramework": "System.CommandLine",
  "latestPaths": {
    "metadataPath": "index/packages/sphererabbitmq.iac.tool/latest/metadata.json",
    "opencliPath": "index/packages/sphererabbitmq.iac.tool/latest/opencli.json",
    "crawlPath": null,
    "xmldocPath": null
  }
}
