{
  "opencli": "0.1-draft",
  "info": {
    "title": "tcdx",
    "version": "0.1.8-beta",
    "description": "Tcdx CLI"
  },
  "x-inspectra": {
    "artifactSource": "crawled-from-help",
    "generator": "InSpectra.Discovery",
    "helpDocumentCount": 2,
    "cliFramework": "System.CommandLine"
  },
  "commands": [
    {
      "name": "unify",
      "hidden": false,
      "description": "Unify the Tcdx file in the specified folder",
      "options": [
        {
          "name": "--recursive",
          "recursive": false,
          "hidden": false,
          "description": "Include subfolders recursively [default: False]",
          "aliases": [
            "-r"
          ]
        },
        {
          "name": "--help",
          "recursive": false,
          "hidden": false,
          "description": "Show help and usage information",
          "aliases": [
            "-?",
            "-h"
          ]
        }
      ],
      "arguments": [
        {
          "name": "FOLDER",
          "required": false,
          "hidden": false,
          "arity": {
            "minimum": 0,
            "maximum": 1
          },
          "description": "Path of the folder containing the Tcdx files to unify"
        },
        {
          "name": "TCDX",
          "required": false,
          "hidden": false,
          "arity": {
            "minimum": 0,
            "maximum": 1
          },
          "description": "Path of the output Tcdx file"
        }
      ]
    }
  ],
  "options": [
    {
      "name": "--version",
      "recursive": false,
      "hidden": false,
      "description": "Show version information"
    },
    {
      "name": "--help",
      "recursive": false,
      "hidden": false,
      "description": "Show help and usage information",
      "aliases": [
        "-?",
        "-h"
      ]
    }
  ]
}
